lakeweed/__init__.py
lakeweed/clickhouse.py
lakeweed/inferencial_parser.py
lakeweed/time_parser.py
lakeweed/util.py
lakeweed-1.2.3.dist-info/LICENSE
lakeweed-1.2.3.dist-info/METADATA
lakeweed-1.2.3.dist-info/WHEEL
lakeweed-1.2.3.dist-info/top_level.txt
lakeweed-1.2.3.dist-info/RECORD
